DAH/DS18B20.py
DAH/MCP23S17.py
DAH/MCP3208.py
DAH/MCP4922.py
DAH/PCF8574.py
DAH/__init__.py
DAH_edinburgh_university-1.1.0.dist-info/LICENSE
DAH_edinburgh_university-1.1.0.dist-info/METADATA
DAH_edinburgh_university-1.1.0.dist-info/WHEEL
DAH_edinburgh_university-1.1.0.dist-info/top_level.txt
DAH_edinburgh_university-1.1.0.dist-info/RECORD
