Metadata-Version: 2.1
Name: DAH-edinburgh-university
Version: 1.1.0
Summary: Access 1-wire, SPI, or I2C devices from Raspberry Pi
Home-page: https://github.com/DruidFish/DAHwebiopiReplace
Author: Benjamin Wynne
Author-email: ben.wynne@gmail.com
Project-URL: Bug Tracker, https://github.com/DruidFish/DAHwebiopiReplace/issues
Classifier: Programming Language :: Python :: 3
Classifier: License :: OSI Approved :: GNU General Public License v3 (GPLv3)
Classifier: Operating System :: Other OS
Requires-Python: >=3.6
License-File: LICENSE
Requires-Dist: spidev
Requires-Dist: smbus
